lib/__init__.py
lib/file_content.py
lib/ignore_handler.py
lib/openai_integration.py
lib/preparation.py
lib/structure.py
TuringCoder-0.1.0.dist-info/LICENSE
TuringCoder-0.1.0.dist-info/METADATA
TuringCoder-0.1.0.dist-info/WHEEL
TuringCoder-0.1.0.dist-info/entry_points.txt
TuringCoder-0.1.0.dist-info/top_level.txt
TuringCoder-0.1.0.dist-info/RECORD
