Metadata-Version: 2.1
Name: TuringCoder
Version: 0.1.0
Summary: TuringCoder is an innovative Python application designed to streamline your workflow through automations, leveraging the power of OpenAI's GPT models. Whether you're organizing your project files, processing text data, or integrating AI-based text generation, DemoApp offers a flexible solution tailored to various needs.
Home-page: https://github.com/FukjemiCZ/TuringCoder
Author: FukjemiCZ
Author-email: turing.coder@fukjemi.cz
License: LICENSE
License-File: LICENSE
Requires-Dist: requests
Requires-Dist: json5
